Metadata-Version: 2.1
Name: colorbytes
Version: 1.0.0
Summary: A simple module to make your Python code come alive with color.
Home-page: UNKNOWN
Author: teremoney
Author-email: teremoney@gmail.com
License: MIT
Keywords: colorbytes
Platform: UNKNOWN
License-File: LICENSE.txt
